busylight/__init__.py
busylight/__main__.py
busylight/busyserve.py
busylight/callbacks.py
busylight/color.py
busylight/controller.py
busylight/global_options.py
busylight/speed.py
busylight/api/__init__.py
busylight/api/busylight_api.py
busylight/api/config.py
busylight/api/dependencies.py
busylight/api/exceptions.py
busylight/api/logging_config.py
busylight/api/main.py
busylight/api/middleware.py
busylight/api/models.py
busylight/api/v1/__init__.py
busylight/api/v1/compat.py
busylight/api/v1/root.py
busylight/api/v1/router.py
busylight/api/v1/effects/__init__.py
busylight/api/v1/effects/router.py
busylight/api/v1/effects/schemas.py
busylight/api/v1/effects/service.py
busylight/api/v1/lights/__init__.py
busylight/api/v1/lights/router.py
busylight/api/v1/lights/schemas.py
busylight/api/v1/lights/service.py
busylight/api/v1/system/__init__.py
busylight/api/v1/system/router.py
busylight/api/v1/system/schemas.py
busylight/api/v2/__init__.py
busylight/effects/__init__.py
busylight/effects/blink.py
busylight/effects/effect.py
busylight/effects/gradient.py
busylight/effects/spectrum.py
busylight/effects/steady.py
busylight/subcommands/__init__.py
busylight/subcommands/blink.py
busylight/subcommands/display.py
busylight/subcommands/fli.py
busylight/subcommands/helpers.py
busylight/subcommands/off.py
busylight/subcommands/on.py
busylight/subcommands/on_new.py
busylight/subcommands/pulse.py
busylight/subcommands/rainbow.py
busylight/subcommands/udev_rules.py
busylight_for_humans-0.45.2.dist-info/METADATA
busylight_for_humans-0.45.2.dist-info/WHEEL
busylight_for_humans-0.45.2.dist-info/entry_points.txt
busylight_for_humans-0.45.2.dist-info/licenses/LICENSE
busylight_for_humans-0.45.2.dist-info/RECORD
