Metadata-Version: 2.4
Name: busylight-for-humans
Version: 0.45.2
Summary: Control USB connected LED lights, like a human.
Author-email: JnyJny <erik.oshaughnessy@gmail.com>
License-Expression: Apache-2.0
License-File: LICENSE
Classifier: Development Status :: 4 - Beta
Classifier: Environment :: Console
Classifier: Intended Audience :: Developers
Classifier: Intended Audience :: End Users/Desktop
Classifier: License :: OSI Approved :: Apache Software License
Classifier: Operating System :: OS Independent
Classifier: Programming Language :: Python
Classifier: Programming Language :: Python :: 3
Classifier: Programming Language :: Python :: 3.9
Classifier: Programming Language :: Python :: 3.10
Classifier: Programming Language :: Python :: 3.11
Classifier: Programming Language :: Python :: 3.12
Classifier: Programming Language :: Python :: 3.13
Classifier: Topic :: System :: Hardware
Classifier: Topic :: Utilities
Requires-Python: <4.0,>=3.11
Requires-Dist: busylight-core>=0.15.2
Requires-Dist: hidapi>=0.14.0.post4
Requires-Dist: loguru>=0.7.3
Requires-Dist: pyserial>=3.5
Requires-Dist: typer>=0.16.0
Requires-Dist: webcolors>=24.11.1
Provides-Extra: docs
Requires-Dist: mkdocs-git-revision-date-localized-plugin>=1.3.0; extra == 'docs'
Requires-Dist: mkdocs-material>=9.5.44; extra == 'docs'
Requires-Dist: mkdocs>=1.6.1; extra == 'docs'
Provides-Extra: web
Requires-Dist: fastapi>=0.115.14; extra == 'web'
Provides-Extra: webapi
Requires-Dist: fastapi>=0.115.14; extra == 'webapi'
Requires-Dist: uvicorn>=0.34.2; extra == 'webapi'
